fbi/__init__.py
fbi/connection.py
fbi_api-1.2.0.dist-info/LICENSE
fbi_api-1.2.0.dist-info/METADATA
fbi_api-1.2.0.dist-info/WHEEL
fbi_api-1.2.0.dist-info/top_level.txt
fbi_api-1.2.0.dist-info/RECORD
