Metadata-Version: 2.1
Name: fbi-api
Version: 1.2.0
Summary: A Python wrapper around the FBI API (unofficial)
Author-email: Richard Mwewa <rly0nheart@duck.com>
License: GNU GENERAL PUBLIC LICENSE
Project-URL: homepage, https://github.com/rly0nheart/fbi-api
Project-URL: documentation, https://github.com/rly0nheart/fbi-api/wiki
Project-URL: repository, https://github.com/rly0nheart/fbi-api.git
Keywords: crime-data,fbi,most-wanted,fbi-project,fbi-crime-api,wanted-persons
Classifier: Development Status :: 5 - Production/Stable
Classifier: Programming Language :: Python :: 3
Classifier: Intended Audience :: Information Technology
Classifier: License :: OSI Approved :: GNU General Public License v3 (GPLv3)
Classifier: Operating System :: OS Independent
Classifier: Natural Language :: English
Classifier: 
Requires-Python: >=3.9
License-File: LICENSE
Requires-Dist: requests
